AUTHORS
CHANGELOG
INSTALL
LICENSE
MANIFEST.in
README
README.rst
THANKS
TODO
setup.cfg
setup.py
django_page_cms.egg-info/PKG-INFO
django_page_cms.egg-info/SOURCES.txt
django_page_cms.egg-info/dependency_links.txt
django_page_cms.egg-info/entry_points.txt
django_page_cms.egg-info/not-zip-safe
django_page_cms.egg-info/requires.txt
django_page_cms.egg-info/top_level.txt
doc/3rd-party-apps.rst
doc/Makefile
doc/changelog.rst
doc/commands.rst
doc/conf.py
doc/contributions.rst
doc/create-blog-application.rst
doc/display-content.rst
doc/edit-content.rst
doc/gerbi.png
doc/index.rst
doc/installation.rst
doc/introduction.rst
doc/navigation-template-tags.rst
doc/page-api.rst
doc/placeholders.rst
doc/settings-list.rst
doc/images/admin-screenshot-1.png
doc/images/admin-screenshot-2.png
doc/images/ckeditor_placeholder.png
doc/images/inline-edit.png
doc/images/rte-light.png
doc/images/section.png
doc/static/main.css
example/__init__.py
example/manage.py
example/settings.py
example/urls.py
example/blog/__init__.py
example/blog/urls.py
example/blog/views.py
example/locale/ru/LC_MESSAGES/django.mo
example/locale/ru/LC_MESSAGES/django.po
example/locale/uk/LC_MESSAGES/django.mo
example/locale/uk/LC_MESSAGES/django.po
example/static/cms/blog.css
example/static/cms/main.css
example/templates/blog-card.html
example/templates/blog-home.html
example/templates/blog-post.html
example/templates/index.html
example/templates/language-selector.html
example/templates/search/search.html
example/templates/search/indexes/pages/page_text.txt
pages/__init__.py
pages/api.py
pages/app_config.py
pages/cache.py
pages/checks.py
pages/command_line.py
pages/context_processors.py
pages/managers.py
pages/models.py
pages/phttp.py
pages/placeholders.py
pages/search_indexes.py
pages/serializers.py
pages/settings.py
pages/test_runner.py
pages/urlconf_registry.py
pages/urls.py
pages/utils.py
pages/views.py
pages/widgets.py
pages/widgets_registry.py
pages/admin/__init__.py
pages/admin/forms.py
pages/admin/utils.py
pages/admin/views.py
pages/fixtures/pages_tests.json
pages/locale/da/LC_MESSAGES/django.mo
pages/locale/da/LC_MESSAGES/django.po
pages/locale/de/LC_MESSAGES/django.mo
pages/locale/de/LC_MESSAGES/django.po
pages/locale/de/LC_MESSAGES/djangojs.mo
