Metadata-Version: 2.1
Name: django-page-cms
Version: 2.0.12
Summary: A tree based Django CMS application
Home-page: https://github.com/batiste/django-page-cms
Author: Batiste Bieler
Author-email: batiste.bieler@gmail.com
License: BSD
Download-URL: http://pypi.python.org/packages/source/d/django-page-cms/django-page-cms-2.0.12.tar.gz
Keywords: django,cms
Platform: UNKNOWN
Classifier: Development Status :: 5 - Production/Stable
Classifier: Environment :: Web Environment
Classifier: Intended Audience :: Developers
Classifier: License :: OSI Approved :: BSD License
Classifier: Operating System :: OS Independent
Classifier: Programming Language :: Python
Classifier: Framework :: Django
Classifier: Programming Language :: Python :: 3.3
Classifier: Programming Language :: Python :: 3.4
Classifier: Programming Language :: Python :: 3.5
Classifier: Programming Language :: Python :: 3.6
Classifier: Programming Language :: JavaScript
Classifier: Topic :: Internet :: WWW/HTTP :: Site Management
Provides-Extra: docs
Provides-Extra: extra
Provides-Extra: full
Provides-Extra: tests
License-File: LICENSE
License-File: AUTHORS
